shake_that_assurance/UnifiedAssuranceAPI.py
shake_that_assurance/__init__.py
shake_that_assurance-0.0.6.dist-info/LICENSE
shake_that_assurance-0.0.6.dist-info/METADATA
shake_that_assurance-0.0.6.dist-info/WHEEL
shake_that_assurance-0.0.6.dist-info/top_level.txt
shake_that_assurance-0.0.6.dist-info/RECORD
