Metadata-Version: 2.1
Name: shake-that-assurance
Version: 0.0.6
Summary: Python api wrapper for Unified Assurance
Author-email: Brian Lee <brian.baligad.lee@zayo.com>
License: Apache License
Project-URL: Homepage, https://github.com/bleetube/shake-that-assurance
Classifier: Programming Language :: Python
Classifier: Programming Language :: Python :: 3
Classifier: Programming Language :: Python :: 3.11
Classifier: Programming Language :: Python :: 3.12
Classifier: Programming Language :: Python :: Implementation :: CPython
Classifier: Programming Language :: Python :: Implementation :: PyPy
Classifier: Topic :: System :: Monitoring
Requires-Python: >=3.11.6
License-File: LICENSE
Requires-Dist: build >=1.2.1
Requires-Dist: requests >=2.31.0
Requires-Dist: pytest >=8.1.1
